[
    {
      "title": "Lorem Isum Kang Sae Sum",
      "video": "https://www.youtube.com/embed/-yCql-VTtHo"
    },
    {
      "title": "Lorem Isum Kang Sae Sum",
      "video": "https://www.youtube.com/embed/-yCql-VTtHo"
    },
    {
      "title": "Lorem Isum Kang Sae Sum",
      "video": "https://www.youtube.com/embed/-yCql-VTtHo"
    },
    {
      "title": "Lorem Isum Kang Sae Sum",
      "video": "https://www.youtube.com/embed/-yCql-VTtHo"
    },
    {
      "title": "Lorem Isum Kang Sae Sum",
      "video": "https://www.youtube.com/embed/-yCql-VTtHo"
    },
    {
      "title": "Lorem Isum Kang Sae Sum",
      "video": "https://www.youtube.com/embed/-yCql-VTtHo"
    }
  ]
  